feature_selection_test/__init__.py
feature_selection_test/feature_selection_test.py
feature_selection_toolkit/__init__.py
feature_selection_toolkit/feature_selection.py
feature_selection_toolkit-1.1.0.dist-info/LICENSE
feature_selection_toolkit-1.1.0.dist-info/METADATA
feature_selection_toolkit-1.1.0.dist-info/WHEEL
feature_selection_toolkit-1.1.0.dist-info/top_level.txt
feature_selection_toolkit-1.1.0.dist-info/RECORD
