Metadata-Version: 2.1
Name: feature_selection_toolkit
Version: 1.1.0
Summary: A comprehensive toolkit for performing various feature selection techniques in machine learning.
Home-page: https://github.com/mevlt01001/feature_selection_toolkit
Author: Mevlüt Başaran
Author-email: mevlutbasaran01@gmail.com
License: MIT License © 2024 Mevlüt Başaran
Project-URL: GitHub, https://github.com/mevlt01001/feature_selection_toolkit
Project-URL: Bug Tracker, https://github.com/mevlt01001/feature_selection_toolkit/issues
Project-URL: LinkedIn, https://www.linkedin.com/in/mevl%C3%BCt-ba%C5%9Faran-b46888251/
Project-URL: Kaggle, https://www.kaggle.com/mevltbaaran
Classifier: Development Status :: 4 - Beta
Classifier: Intended Audience :: Developers
Classifier: Intended Audience :: Science/Research
Classifier: License :: OSI Approved :: MIT License
Classifier: Programming Language :: Python :: 3
Classifier: Programming Language :: Python :: 3.8
Classifier: Programming Language :: Python :: 3.9
Classifier: Programming Language :: Python :: 3.10
Classifier: Programming Language :: Python :: 3.11
Classifier: Operating System :: OS Independent
Classifier: Topic :: Software Development :: Libraries :: Python Modules
Classifier: Topic :: Scientific/Engineering :: Information Analysis
Classifier: Topic :: Scientific/Engineering :: Artificial Intelligence
Classifier: Topic :: Scientific/Engineering :: Visualization
Classifier: Topic :: Software Development :: Libraries
Requires-Python: >=3.8
License-File: LICENSE
Requires-Dist: pandas
Requires-Dist: scikit-learn
Requires-Dist: tqdm
Requires-Dist: xgboost
Requires-Dist: statsmodels
Requires-Dist: joblib
Requires-Dist: matplotlib
Requires-Dist: numpy
